liarcom/__init__.py
liarcom/__main__.py
liarcom/liarcom.py
liarcom/main_window.py
liarcom/main_window_controller.py
liarcom/tools.py
liarcom-1.0.0.dist-info/DESCRIPTION.rst
liarcom-1.0.0.dist-info/METADATA
liarcom-1.0.0.dist-info/RECORD
liarcom-1.0.0.dist-info/WHEEL
liarcom-1.0.0.dist-info/metadata.json
liarcom-1.0.0.dist-info/top_level.txt
