Metadata-Version: 2.0
Name: liarcom
Version: 1.0.0
Summary: 第三方Drcom登陆器
Home-page: https://github.com/Everyb0dyLies/liarcom
Author: 高铭
Author-email: gaomingshsf@hotmail.com
License: GNU General Public License v3 (GPLv3)
Platform: all
Classifier: Development Status :: 3 - Alpha
Classifier: Natural Language :: Chinese (Simplified)
Classifier: Operating System :: Microsoft :: Windows :: Windows 10
Classifier: Operating System :: MacOS
Classifier: Operating System :: POSIX :: Linux
Classifier: Environment :: Console
Classifier: Environment :: MacOS X
Classifier: Environment :: Win32 (MS Windows)
Classifier: Intended Audience :: Developers
Classifier: License :: OSI Approved :: GNU General Public License v3 (GPLv3)
Classifier: Programming Language :: Python :: 3
Classifier: Programming Language :: Python :: 3.5
Classifier: Programming Language :: Python :: 3.6
Requires-Dist: PyQt5
